<?xml version="1.0" encoding="UTF-8"?>

<SPEAKER_SETUP VERSION="4.0.0" SPAT_MODE="Cube" DIFFUSION="0.0" GENERAL_MUTE="0">
  <SPEAKER_GROUP ID="Main" CARTESIAN_POSITION="(0, 0, 0)">
    <SPEAKER ID="1" STATE="normal" GAIN="0.0" DIRECT_OUT_ONLY="0" CARTESIAN_POSITION="(-0.707108, 0.707107, -9.47812e-08)"
             FREQ="60.0"/>
    <SPEAKER ID="2" STATE="normal" GAIN="0.0" DIRECT_OUT_ONLY="0" CARTESIAN_POSITION="(0.707107, 0.707107, -9.47812e-08)"
             FREQ="60.0"/>
    <SPEAKER ID="3" STATE="normal" GAIN="0.0" DIRECT_OUT_ONLY="0" CARTESIAN_POSITION="(-0.707108, -0.707107, -9.47812e-08)"
             FREQ="60.0"/>
    <SPEAKER_GROUP ID="new group" UUID="d06a99b27a494adda0a78f44e753226a" CARTESIAN_POSITION="(0.52, -0.12, 0.33)">
      <SPEAKER CARTESIAN_POSITION="(0, 0.026287, 0.0425323)" ID="6" UUID="411d2ff7271a4d368af4ce4a57622230"
               STATE="normal" GAIN="0.0" DIRECT_OUT_ONLY="0"/>
      <SPEAKER CARTESIAN_POSITION="(0, 0.026287, -0.0425323)" ID="7" UUID="b9cb3ef8d0fd42959b6f5fb1461a1175"
               STATE="normal" GAIN="0.0" DIRECT_OUT_ONLY="0"/>
      <SPEAKER CARTESIAN_POSITION="(0, -0.026287, 0.0425323)" ID="8" UUID="49a304c6ad0041af92e24bb8e0bdf17e"
               STATE="normal" GAIN="0.0" DIRECT_OUT_ONLY="0"/>
      <SPEAKER CARTESIAN_POSITION="(0, -0.026287, -0.0425323)" ID="9" UUID="24e6b91f35dd4632a53fbcb85b960de2"
               STATE="normal" GAIN="0.0" DIRECT_OUT_ONLY="0"/>
      <SPEAKER CARTESIAN_POSITION="(0.026287, 0.0425323, 0)" ID="10" UUID="581afc94e144456eb184783e032c687c"
               STATE="normal" GAIN="0.0" DIRECT_OUT_ONLY="0"/>
      <SPEAKER CARTESIAN_POSITION="(0.026287, -0.0425323, 0)" ID="11" UUID="13750caa474e440596e748ecaeebc475"
               STATE="normal" GAIN="0.0" DIRECT_OUT_ONLY="0"/>
      <SPEAKER CARTESIAN_POSITION="(-0.026287, 0.0425323, 0)" ID="12" UUID="4d9890ac479a45938e7864ec42451a6d"
               STATE="normal" GAIN="0.0" DIRECT_OUT_ONLY="0"/>
      <SPEAKER CARTESIAN_POSITION="(-0.026287, -0.0425323, 0)" ID="13" UUID="64ee76dc97984d8c84e9c2d79a1d276d"
               STATE="normal" GAIN="0.0" DIRECT_OUT_ONLY="0"/>
      <SPEAKER CARTESIAN_POSITION="(0.0425323, 0, 0.026287)" ID="14" UUID="bfc590340ca44726b50085f9274d09a0"
               STATE="normal" GAIN="0.0" DIRECT_OUT_ONLY="0"/>
      <SPEAKER CARTESIAN_POSITION="(0.0425323, 0, -0.026287)" ID="15" UUID="b171805c0c9d48aba9875eddeaed71fe"
               STATE="normal" GAIN="0.0" DIRECT_OUT_ONLY="0"/>
      <SPEAKER CARTESIAN_POSITION="(-0.0425323, 0, 0.026287)" ID="16" UUID="c191f22fd1d845bab178e9988d79939b"
               STATE="normal" GAIN="0.0" DIRECT_OUT_ONLY="0"/>
      <SPEAKER CARTESIAN_POSITION="(-0.0425323, 0, -0.026287)" ID="17" UUID="32b0295f3f5c476ea1a679a56e2f142e"
               STATE="normal" GAIN="0.0" DIRECT_OUT_ONLY="0"/>
    </SPEAKER_GROUP>
    <SPEAKER ID="4" STATE="normal" GAIN="0.0" DIRECT_OUT_ONLY="0" CARTESIAN_POSITION="(0.707107, -0.707107, -9.47812e-08)"
             FREQ="60.0"/>
    <SPEAKER ID="5" STATE="normal" GAIN="0.0" DIRECT_OUT_ONLY="1" CARTESIAN_POSITION="(-1.31746e-07, 1.39, -1.31746e-07)"/>
  </SPEAKER_GROUP>
</SPEAKER_SETUP>
